odoo/addons/l10n_it_riba_queued/README.rst
odoo/addons/l10n_it_riba_queued/__init__.py
odoo/addons/l10n_it_riba_queued/__manifest__.py
odoo/addons/l10n_it_riba_queued/i18n/it.po
odoo/addons/l10n_it_riba_queued/i18n/l10n_it_riba_queued.pot
odoo/addons/l10n_it_riba_queued/models/__init__.py
odoo/addons/l10n_it_riba_queued/models/riba_line.py
odoo/addons/l10n_it_riba_queued/readme/CONTRIBUTORS.md
odoo/addons/l10n_it_riba_queued/readme/DESCRIPTION.md
odoo/addons/l10n_it_riba_queued/readme/USAGE.md
odoo/addons/l10n_it_riba_queued/static/description/icon.png
odoo/addons/l10n_it_riba_queued/static/description/index.html
odoo/addons/l10n_it_riba_queued/tests/__init__.py
odoo/addons/l10n_it_riba_queued/tests/test_riba.py
odoo/addons/l10n_it_riba_queued/wizards/__init__.py
odoo/addons/l10n_it_riba_queued/wizards/wizard_riba_multiple_payment.py
odoo/addons/l10n_it_riba_queued/wizards/wizard_riba_multiple_payment_views.xml
odoo14_addon_l10n_it_riba_queued-14.0.1.2.0.dist-info/METADATA
odoo14_addon_l10n_it_riba_queued-14.0.1.2.0.dist-info/WHEEL
odoo14_addon_l10n_it_riba_queued-14.0.1.2.0.dist-info/top_level.txt
odoo14_addon_l10n_it_riba_queued-14.0.1.2.0.dist-info/RECORD
